{
    "idSave": 16,
    "isFirstSession": false,
    "language": "ru",
    "promptDone": false,
    "money": 1,
    "newPlayerName": "Hello!",
    "openLevels": [
        false,
        true,
        false
    ],
    "levelsPassed": 2,
    "currencies": [
        {
            "Key": "gold",
            "Value": 40.0
        }
    ],
    "purchases": [
        "-368270586",
        "-753201110",
        "-1329021927"
    ],
    "weaponSelectedIndexes": [
        {
            "WeaponKey": "Sniper 01",
            "Indexes": {
                "scopeDefaultShow": true,
                "scopeIndex": -1,
                "muzzleIndex": 0,
                "laserIndex": -1,
                "gripIndex": -1,
                "magazineIndex": 0
            }
        }
    ]
}